novi/client/__init__.py
novi/client/activations/__init__.py
novi/client/activations/activation_util.py
novi/client/activations/and_activation.py
novi/client/activations/base_combination_activation.py
novi/client/activations/date_time_activation.py
novi/client/activations/or_activation.py
novi/client/activations/weighted_random_activation.py
novi/client/database.py
novi/client/flag.py
novi/core/__init__.py
novi/core/models.py
novi/web/__init__.py
novi/web/evaluated_flags_endpoint.py
novi/web/flags_endpoint.py
novi/web/README.md
novi_activations/__empty__/__init__.py
novi_activations/README.md
novi-0.4.2.dist-info/LICENSE
novi-0.4.2.dist-info/METADATA
novi-0.4.2.dist-info/WHEEL
novi-0.4.2.dist-info/RECORD
