Metadata-Version: 2.1
Name: novi
Version: 0.4.2
Summary: A simple yet powerful feature flag and multivariate testing platform built in Python
Home-page: https://github.com/vdevigere/Novi
License: GPL-3.0-only
Author: vdevigere
Author-email: vdevigere+git@gmail.com
Requires-Python: >=3.11,<4.0
Classifier: License :: OSI Approved :: GNU General Public License v3 (GPLv3)
Classifier: Programming Language :: Python
Classifier: Programming Language :: Python :: 3
Classifier: Programming Language :: Python :: 3.11
Classifier: Programming Language :: Python :: 3.12
Classifier: Topic :: Software Development :: Testing
Requires-Dist: Flask (>=3.0.0,<4.0.0)
Requires-Dist: SQLAlchemy (>=2.0.23,<3.0.0)
Requires-Dist: requests (>=2.31.0,<3.0.0)
Project-URL: Documentation, https://github.com/vdevigere/Novi
Project-URL: Repository, https://github.com/vdevigere/Novi
